.bumpversion.cfg
.gitignore
.travis.yml
COPYING
README.md
README.rst
requirements.in
requirements.txt
setup.py
wercker.yml
dlpa/__init__.py
dlpa/client.py
dlpa/dlpa.proto
dlpa/dlpa_pb2.py
dlpa/dlpa_pb2_grpc.py
dlpa/key.py
dlpa/server.py
dlpa/util.py
docs/Makefile
docs/source/.gitignore
docs/source/conf.py
docs/source/index.rst
docs/source/_templates/footer.html
docs/source/_templates/layout.html
psi_dlpa.egg-info/PKG-INFO
psi_dlpa.egg-info/SOURCES.txt
psi_dlpa.egg-info/dependency_links.txt
psi_dlpa.egg-info/entry_points.txt
psi_dlpa.egg-info/requires.txt
psi_dlpa.egg-info/top_level.txt
tests/__init__.py
tests/dlpa_test.py
tests/rpc_test.py
tests/test_suite.py