Metadata-Version: 1.1
Name: psi-dlpa
Version: 0.3.0
Summary: Client/Server for Distributed Laplace Perturbation Algorithm
Home-page: https://github.com/jkawamoto/psi-dlpa
Author: Junpei Kawamoto
Author-email: kawamoto.junpei@gmail.com
License: GPLv3
Platform: UNKNOWN
Classifier: Development Status :: 3 - Alpha
Classifier: Intended Audience :: Science/Research
Classifier: License :: OSI Approved :: GNU General Public License v3 (GPLv3)
Classifier: Natural Language :: English
Classifier: Programming Language :: Python
Classifier: Topic :: Software Development :: Libraries
Classifier: Topic :: Scientific/Engineering :: Information Analysis
